projet/__init__.py
projet/__main__.py
projet/agents/agent.py
projet/agents/apprentissage_RL/agent.py
projet/agents/apprentissage_RL/images/q_formula.PNG
projet/agents/human.py
projet/agents/node.py
projet/agents/optimisation_MinMax/images/MinMax.png
projet/agents/optimisation_MinMax/images/Plminmax.gif
projet/agents/optimisation_MinMax/minimax.py
projet/agents/optimisation_MinMax/tree/draw_tree.py
projet/agents/optimisation_MinMax/tree/game_tree.py
projet/agents/optimisation_MinMax/tree/Jeu_Nim_tree.py
projet/agents/optimisation_MinMax/tree/minimax_tree.py
projet/agents/random.py
projet/games/game.py
projet/games/jeu_Nim.py
projet/games/TicTacToe_new/jeu_TicTacToe.py
projet/games/TicTacToe_new/player_informations.py
projet/games/TicTacToe_old/jeu_TicTacToe.py
projet/Go/Plateau-old.py
projet/Go/Plateau.py
projet/Quoridor/Joueur.py
projet/Quoridor/Main.py
projet/Quoridor/Plateau.py
projet/Quoridor/version0/Joueur.py
projet/Quoridor/version0/Main.py
projet/Quoridor/version0/Plateau.py
projet/Quoridor/version1/Joueur.py
projet/Quoridor/version1/Main.py
projet/Quoridor/version1/Plateau.py
projet/utilities/agent_informations.py
projet/utilities/agent_victories.py
projet/utilities/plot.py
projet/utilities/utilities.py
boardgameai-0.1.0.dist-info/LICENSE
boardgameai-0.1.0.dist-info/WHEEL
boardgameai-0.1.0.dist-info/METADATA
boardgameai-0.1.0.dist-info/RECORD
