Metadata-Version: 2.1
Name: boardgameai
Version: 0.1.0
Summary: an API for playing turn by turn games using IA
Author: Aurelien Castel
Author-email: dummy@g.com
Requires-Python: >=3.7,<4.0
Classifier: Programming Language :: Python :: 3
Classifier: Programming Language :: Python :: 3.7
Classifier: Programming Language :: Python :: 3.8
Requires-Dist: matplotlib (>=3.1.3,<4.0.0)
